{
    "__package_slug": "resume",
    "_checkout": null,
    "_output_dir": "/home/luiz/Documents/projects",
    "_repo_dir": "/home/luiz/.cookiecutters/cookiecutter-dinkin-flicka",
    "_template": "https://github.com/luizdesuo/cookiecutter-dinkin-flicka.git",
    "author": "Luiz Desu\u00f3 Neto",
    "copyright_year": "2024",
    "data_version_control": false,
    "defensive_programming": false,
    "development_status": "None",
    "email": "luizdesuo@gmail.com",
    "friendly_name": "Resume",
    "github_user": "luizdesuo",
    "license": "None",
    "package_short_description": "my resume",
    "package_version": "0.0.0",
    "project_name": "resume",
    "publish": false,
    "python_version": "3.11"
}
